fastapi_healthcheck_sqlalchemy/__init__.py
fastapi_healthcheck_sqlalchemy/service.py
fastapi_healthcheck_sqlalchemy-0.1.0.dist-info/WHEEL
fastapi_healthcheck_sqlalchemy-0.1.0.dist-info/METADATA
fastapi_healthcheck_sqlalchemy-0.1.0.dist-info/RECORD
