Metadata-Version: 2.1
Name: fastapi-healthcheck-sqlalchemy
Version: 0.1.0
Summary: A service to check the health of your applications SQLAlchemy connection.
Home-page: https://github.com/jtom38/fastapi_healthcheck_sqlalchemy
Author: James Tombleson
Author-email: luther38@gmail.com
Requires-Python: >=3.9,<4.0
Classifier: Development Status :: 3 - Alpha
Classifier: Framework :: FastAPI
Classifier: Programming Language :: Python :: 3
Classifier: Programming Language :: Python :: 3.10
Classifier: Programming Language :: Python :: 3.9
Requires-Dist: FastAPI-SQLAlchemy (>=0.2.1,<0.3.0)
Requires-Dist: fastapi-healthcheck (>=0.2.2,<0.3.0)
Project-URL: Repository, https://github.com/jtom38/fastapi_healthcheck_sqlalchemy
